[
  {
    "id": "eml-0001",
    "partnerId": "prt-029",
    "partnerName": "Vancouver Voice",
    "from": "viktor.novak@vancouvervoice.example",
    "to": "james.whitaker@3cx-sales.example",
    "date": "2024-11-25",
    "subject": "Meeting recap & action items",
    "sentiment": "positive",
    "status": "sent",
    "body": "Viktor Novak wrote:\nWe need pricing for 47 SC and clarity on private cloud vs hosted.\n\nThanks"
  },
  {
    "id": "eml-0002",
    "partnerId": "prt-049",
    "partnerName": "Oslo Voice",
    "from": "viktor.novak@oslovoice.example",
    "to": "james.whitaker@3cx-sales.example",
    "date": "2024-06-01",
    "subject": "SC expansion quote",
    "sentiment": "neutral",
    "status": "sent",
    "body": "Viktor Novak wrote:\nWe need pricing for 121 SC and clarity on private cloud vs hosted.\n\nThanks"
  },
  {
    "id": "eml-0003",
    "partnerId": "prt-034",
    "partnerName": "Buenos Aires UC",
    "from": "elena.vogel@3cx-sales.example",
    "to": "fatima.hassan@buenosairesuc.example",
    "date": "2024-11-06",
    "subject": "Follow-up: partner QBR",
    "sentiment": "positive",
    "status": "sent",
    "body": "Hello Fatima Hassan,\n\nFollowing our discussion on Buenos Aires UC's deployment, attached is the Enterprise outline with SC counts.\n\nElena"
  },
  {
    "id": "eml-0004",
    "partnerId": "prt-028",
    "partnerName": "Toronto UC",
    "from": "ana.popescu@torontouc.example",
    "to": "jordan.lee@3cx-sales.example",
    "date": "2024-11-17",
    "subject": "Hosting renewal — next steps",
    "sentiment": "negative",
    "status": "sent",
    "body": "Ana Popescu wrote:\nWe need pricing for 226 SC and clarity on private cloud vs hosted.\n\nThanks"
  },
  {
    "id": "eml-0005",
    "partnerId": "prt-019",
    "partnerName": "Lagos Connect",
    "from": "viktor.novak@lagosconnect.example",
    "to": "sam.rivera@3cx-sales.example",
    "date": "2024-01-03",
    "subject": "License alignment check",
    "sentiment": "neutral",
    "status": "sent",
    "body": "Viktor Novak wrote:\nWe need pricing for 131 SC and clarity on private cloud vs hosted.\n\nThanks"
  },
  {
    "id": "eml-0006",
    "partnerId": "prt-008",
    "partnerName": "Alpine Voice Systems",
    "from": "james.whitaker@3cx-sales.example",
    "to": "ana.popescu@alpinevoicesystems.example",
    "date": "2026-04-30",
    "subject": "License alignment check",
    "sentiment": "neutral",
    "status": "scheduled_draft",
    "body": "Hello Ana Popescu,\n\nFollowing our discussion on Alpine Voice Systems's deployment, attached is the Enterprise outline with SC counts.\n\nJames"
  },
  {
    "id": "eml-0007",
    "partnerId": "prt-023",
    "partnerName": "Seoul Voice Pro",
    "from": "priya.desai@3cx-sales.example",
    "to": "luis.garcía@seoulvoicepro.example",
    "date": "2024-02-08",
    "subject": "Hosting renewal — next steps",
    "sentiment": "negative",
    "status": "sent",
    "body": "Hello Luis García,\n\nFollowing our discussion on Seoul Voice Pro's deployment, attached is the Enterprise outline with SC counts.\n\nPriya"
  },
  {
    "id": "eml-0008",
    "partnerId": "prt-043",
    "partnerName": "Brussels Connect",
    "from": "luis.garcía@brusselsconnect.example",
    "to": "sam.rivera@3cx-sales.example",
    "date": "2024-07-19",
    "subject": "PBX renewal options",
    "sentiment": "positive",
    "status": "sent",
    "body": "Luis García wrote:\nWe need pricing for 248 SC and clarity on private cloud vs hosted.\n\nThanks"
  },
  {
    "id": "eml-0009",
    "partnerId": "prt-009",
    "partnerName": "Pacific Ring Networks",
    "from": "jordan.lee@3cx-sales.example",
    "to": "viktor.novak@pacificringnetworks.example",
    "date": "2024-02-24",
    "subject": "Hosting renewal — next steps",
    "sentiment": "positive",
    "status": "sent",
    "body": "Hello Viktor Novak,\n\nFollowing our discussion on Pacific Ring Networks's deployment, attached is the Pro outline with SC counts.\n\nJordan"
  },
  {
    "id": "eml-0010",
    "partnerId": "prt-003",
    "partnerName": "CloudVoice DACH",
    "from": "priya.desai@3cx-sales.example",
    "to": "luis.garcía@cloudvoicedach.example",
    "date": "2024-05-17",
    "subject": "Hosting renewal — next steps",
    "sentiment": "negative",
    "status": "sent",
    "body": "Hello Luis García,\n\nFollowing our discussion on CloudVoice DACH's deployment, attached is the Pro outline with SC counts.\n\nPriya"
  },
  {
    "id": "eml-0011",
    "partnerId": "prt-029",
    "partnerName": "Vancouver Voice",
    "from": "viktor.novak@vancouvervoice.example",
    "to": "jordan.lee@3cx-sales.example",
    "date": "2025-01-25",
    "subject": "Meeting recap & action items",
    "sentiment": "neutral",
    "status": "sent",
    "body": "Viktor Novak wrote:\nWe need pricing for 64 SC and clarity on private cloud vs hosted.\n\nThanks"
  },
  {
    "id": "eml-0012",
    "partnerId": "prt-031",
    "partnerName": "Mexico City VoIP",
    "from": "marco.silva@mexicocityvoip.example",
    "to": "morgan.blake@3cx-sales.example",
    "date": "2025-03-25",
    "subject": "Follow-up: partner QBR",
    "sentiment": "neutral",
    "status": "sent",
    "body": "Marco Silva wrote:\nWe need pricing for 111 SC and clarity on private cloud vs hosted.\n\nThanks"
  },
  {
    "id": "eml-0013",
    "partnerId": "prt-024",
    "partnerName": "Mumbai Telecom Hub",
    "from": "chris.okonkwo@3cx-sales.example",
    "to": "fatima.hassan@mumbaitelecomhub.example",
    "date": "2025-04-25",
    "subject": "License alignment check",
    "sentiment": "neutral",
    "status": "sent",
    "body": "Hello Fatima Hassan,\n\nFollowing our discussion on Mumbai Telecom Hub's deployment, attached is the Standard outline with SC counts.\n\nChris"
  },
  {
    "id": "eml-0014",
    "partnerId": "prt-016",
    "partnerName": "Red Sea Voice",
    "from": "yuki.tanaka@redseavoice.example",
    "to": "tomasz.kowalski@3cx-sales.example",
    "date": "2025-01-12",
    "subject": "License alignment check",
    "sentiment": "negative",
    "status": "sent",
    "body": "Yuki Tanaka wrote:\nWe need pricing for 19 SC and clarity on private cloud vs hosted.\n\nThanks"
  },
  {
    "id": "eml-0015",
    "partnerId": "prt-029",
    "partnerName": "Vancouver Voice",
    "from": "tomasz.kowalski@3cx-sales.example",
    "to": "viktor.novak@vancouvervoice.example",
    "date": "2024-08-21",
    "subject": "Hosting renewal — next steps",
    "sentiment": "positive",
    "status": "sent",
    "body": "Hello Viktor Novak,\n\nFollowing our discussion on Vancouver Voice's deployment, attached is the Enterprise outline with SC counts.\n\nTomasz"
  },
  {
    "id": "eml-0016",
    "partnerId": "prt-044",
    "partnerName": "Amsterdam UC",
    "from": "fatima.hassan@amsterdamuc.example",
    "to": "james.whitaker@3cx-sales.example",
    "date": "2024-02-17",
    "subject": "License alignment check",
    "sentiment": "neutral",
    "status": "sent",
    "body": "Fatima Hassan wrote:\nWe need pricing for 189 SC and clarity on private cloud vs hosted.\n\nThanks"
  },
  {
    "id": "eml-0017",
    "partnerId": "prt-018",
    "partnerName": "Cape Town Comms",
    "from": "priya.desai@3cx-sales.example",
    "to": "ana.popescu@capetowncomms.example",
    "date": "2024-11-14",
    "subject": "Follow-up: partner QBR",
    "sentiment": "positive",
    "status": "sent",
    "body": "Hello Ana Popescu,\n\nFollowing our discussion on Cape Town Comms's deployment, attached is the Pro outline with SC counts.\n\nPriya"
  },
  {
    "id": "eml-0018",
    "partnerId": "prt-049",
    "partnerName": "Oslo Voice",
    "from": "viktor.novak@oslovoice.example",
    "to": "priya.desai@3cx-sales.example",
    "date": "2024-09-22",
    "subject": "Meeting recap & action items",
    "sentiment": "neutral",
    "status": "sent",
    "body": "Viktor Novak wrote:\nWe need pricing for 224 SC and clarity on private cloud vs hosted.\n\nThanks"
  },
  {
    "id": "eml-0019",
    "partnerId": "prt-026",
    "partnerName": "Melbourne Voice",
    "from": "alex.chen@3cx-sales.example",
    "to": "yuki.tanaka@melbournevoice.example",
    "date": "2024-03-16",
    "subject": "PBX renewal options",
    "sentiment": "positive",
    "status": "sent",
    "body": "Hello Yuki Tanaka,\n\nFollowing our discussion on Melbourne Voice's deployment, attached is the Standard outline with SC counts.\n\nAlex"
  },
  {
    "id": "eml-0020",
    "partnerId": "prt-027",
    "partnerName": "Auckland Connect",
    "from": "diego.ruiz@aucklandconnect.example",
    "to": "elena.vogel@3cx-sales.example",
    "date": "2024-09-03",
    "subject": "Meeting recap & action items",
    "sentiment": "neutral",
    "status": "sent",
    "body": "Diego Ruiz wrote:\nWe need pricing for 63 SC and clarity on private cloud vs hosted.\n\nThanks"
  },
  {
    "id": "eml-0021",
    "partnerId": "prt-037",
    "partnerName": "Budapest Connect",
    "from": "diego.ruiz@budapestconnect.example",
    "to": "elena.vogel@3cx-sales.example",
    "date": "2025-01-26",
    "subject": "Hosting renewal — next steps",
    "sentiment": "positive",
    "status": "sent",
    "body": "Diego Ruiz wrote:\nWe need pricing for 30 SC and clarity on private cloud vs hosted.\n\nThanks"
  },
  {
    "id": "eml-0022",
    "partnerId": "prt-046",
    "partnerName": "Glasgow Ring",
    "from": "james.whitaker@3cx-sales.example",
    "to": "yuki.tanaka@glasgowring.example",
    "date": "2025-03-09",
    "subject": "License alignment check",
    "sentiment": "neutral",
    "status": "sent",
    "body": "Hello Yuki Tanaka,\n\nFollowing our discussion on Glasgow Ring's deployment, attached is the Enterprise outline with SC counts.\n\nJames"
  },
  {
    "id": "eml-0023",
    "partnerId": "prt-032",
    "partnerName": "São Paulo Ring",
    "from": "ingrid.berg@sopauloring.example",
    "to": "sam.rivera@3cx-sales.example",
    "date": "2024-04-25",
    "subject": "SC expansion quote",
    "sentiment": "positive",
    "status": "sent",
    "body": "Ingrid Berg wrote:\nWe need pricing for 171 SC and clarity on private cloud vs hosted.\n\nThanks"
  },
  {
    "id": "eml-0024",
    "partnerId": "prt-029",
    "partnerName": "Vancouver Voice",
    "from": "viktor.novak@vancouvervoice.example",
    "to": "priya.desai@3cx-sales.example",
    "date": "2024-11-20",
    "subject": "License alignment check",
    "sentiment": "neutral",
    "status": "sent",
    "body": "Viktor Novak wrote:\nWe need pricing for 28 SC and clarity on private cloud vs hosted.\n\nThanks"
  },
  {
    "id": "eml-0025",
    "partnerId": "prt-010",
    "partnerName": "Great Lakes UC",
    "from": "alex.chen@3cx-sales.example",
    "to": "zara.khan@greatlakesuc.example",
    "date": "2026-05-01",
    "subject": "PBX renewal options",
    "sentiment": "neutral",
    "status": "scheduled_draft",
    "body": "Hello Zara Khan,\n\nFollowing our discussion on Great Lakes UC's deployment, attached is the Enterprise outline with SC counts.\n\nAlex"
  },
  {
    "id": "eml-0026",
    "partnerId": "prt-001",
    "partnerName": "VoIP Partners Nordic",
    "from": "sam.rivera@3cx-sales.example",
    "to": "marco.silva@voippartnersnordic.example",
    "date": "2024-06-27",
    "subject": "Hosting renewal — next steps",
    "sentiment": "positive",
    "status": "sent",
    "body": "Hello Marco Silva,\n\nFollowing our discussion on VoIP Partners Nordic's deployment, attached is the Standard outline with SC counts.\n\nSam"
  },
  {
    "id": "eml-0027",
    "partnerId": "prt-021",
    "partnerName": "Singapore Ring",
    "from": "marco.silva@singaporering.example",
    "to": "priya.desai@3cx-sales.example",
    "date": "2026-04-23",
    "subject": "SC expansion quote",
    "sentiment": "negative",
    "status": "scheduled_draft",
    "body": "Marco Silva wrote:\nWe need pricing for 162 SC and clarity on private cloud vs hosted.\n\nThanks"
  },
  {
    "id": "eml-0028",
    "partnerId": "prt-027",
    "partnerName": "Auckland Connect",
    "from": "priya.desai@3cx-sales.example",
    "to": "diego.ruiz@aucklandconnect.example",
    "date": "2024-08-03",
    "subject": "PBX renewal options",
    "sentiment": "negative",
    "status": "sent",
    "body": "Hello Diego Ruiz,\n\nFollowing our discussion on Auckland Connect's deployment, attached is the Enterprise outline with SC counts.\n\nPriya"
  },
  {
    "id": "eml-0029",
    "partnerId": "prt-023",
    "partnerName": "Seoul Voice Pro",
    "from": "chris.okonkwo@3cx-sales.example",
    "to": "luis.garcía@seoulvoicepro.example",
    "date": "2024-02-05",
    "subject": "License alignment check",
    "sentiment": "neutral",
    "status": "sent",
    "body": "Hello Luis García,\n\nFollowing our discussion on Seoul Voice Pro's deployment, attached is the Standard outline with SC counts.\n\nChris"
  },
  {
    "id": "eml-0030",
    "partnerId": "prt-025",
    "partnerName": "Sydney PBX Group",
    "from": "henrik.larsson@sydneypbxgroup.example",
    "to": "james.whitaker@3cx-sales.example",
    "date": "2024-06-16",
    "subject": "Hosting renewal — next steps",
    "sentiment": "positive",
    "status": "sent",
    "body": "Henrik Larsson wrote:\nWe need pricing for 241 SC and clarity on private cloud vs hosted.\n\nThanks"
  },
  {
    "id": "eml-0031",
    "partnerId": "prt-007",
    "partnerName": "Mediterranean UC",
    "from": "priya.desai@3cx-sales.example",
    "to": "diego.ruiz@mediterraneanuc.example",
    "date": "2024-02-09",
    "subject": "Meeting recap & action items",
    "sentiment": "neutral",
    "status": "sent",
    "body": "Hello Diego Ruiz,\n\nFollowing our discussion on Mediterranean UC's deployment, attached is the Standard outline with SC counts.\n\nPriya"
  },
  {
    "id": "eml-0032",
    "partnerId": "prt-005",
    "partnerName": "Atlantic PBX Group",
    "from": "sofia.martins@3cx-sales.example",
    "to": "henrik.larsson@atlanticpbxgroup.example",
    "date": "2024-06-25",
    "subject": "Hosting renewal — next steps",
    "sentiment": "neutral",
    "status": "sent",
    "body": "Hello Henrik Larsson,\n\nFollowing our discussion on Atlantic PBX Group's deployment, attached is the Standard outline with SC counts.\n\nSofia"
  },
  {
    "id": "eml-0033",
    "partnerId": "prt-037",
    "partnerName": "Budapest Connect",
    "from": "elena.vogel@3cx-sales.example",
    "to": "diego.ruiz@budapestconnect.example",
    "date": "2025-02-13",
    "subject": "Follow-up: partner QBR",
    "sentiment": "negative",
    "status": "sent",
    "body": "Hello Diego Ruiz,\n\nFollowing our discussion on Budapest Connect's deployment, attached is the Standard outline with SC counts.\n\nElena"
  },
  {
    "id": "eml-0034",
    "partnerId": "prt-019",
    "partnerName": "Lagos Connect",
    "from": "jordan.lee@3cx-sales.example",
    "to": "viktor.novak@lagosconnect.example",
    "date": "2024-08-21",
    "subject": "Follow-up: partner QBR",
    "sentiment": "neutral",
    "status": "sent",
    "body": "Hello Viktor Novak,\n\nFollowing our discussion on Lagos Connect's deployment, attached is the Pro outline with SC counts.\n\nJordan"
  },
  {
    "id": "eml-0035",
    "partnerId": "prt-036",
    "partnerName": "Prague Ring",
    "from": "priya.desai@3cx-sales.example",
    "to": "yuki.tanaka@praguering.example",
    "date": "2024-02-21",
    "subject": "License alignment check",
    "sentiment": "negative",
    "status": "sent",
    "body": "Hello Yuki Tanaka,\n\nFollowing our discussion on Prague Ring's deployment, attached is the Pro outline with SC counts.\n\nPriya"
  },
  {
    "id": "eml-0036",
    "partnerId": "prt-023",
    "partnerName": "Seoul Voice Pro",
    "from": "luis.garcía@seoulvoicepro.example",
    "to": "james.whitaker@3cx-sales.example",
    "date": "2025-04-04",
    "subject": "SC expansion quote",
    "sentiment": "neutral",
    "status": "sent",
    "body": "Luis García wrote:\nWe need pricing for 185 SC and clarity on private cloud vs hosted.\n\nThanks"
  },
  {
    "id": "eml-0037",
    "partnerId": "prt-050",
    "partnerName": "Stockholm Ring",
    "from": "chris.okonkwo@3cx-sales.example",
    "to": "zara.khan@stockholmring.example",
    "date": "2025-03-09",
    "subject": "Follow-up: partner QBR",
    "sentiment": "neutral",
    "status": "sent",
    "body": "Hello Zara Khan,\n\nFollowing our discussion on Stockholm Ring's deployment, attached is the Standard outline with SC counts.\n\nChris"
  },
  {
    "id": "eml-0038",
    "partnerId": "prt-038",
    "partnerName": "Bucharest UC",
    "from": "tomasz.kowalski@3cx-sales.example",
    "to": "ana.popescu@bucharestuc.example",
    "date": "2024-07-26",
    "subject": "Follow-up: partner QBR",
    "sentiment": "neutral",
    "status": "sent",
    "body": "Hello Ana Popescu,\n\nFollowing our discussion on Bucharest UC's deployment, attached is the Pro outline with SC counts.\n\nTomasz"
  },
  {
    "id": "eml-0039",
    "partnerId": "prt-017",
    "partnerName": "Sahara UC Partners",
    "from": "chris.okonkwo@3cx-sales.example",
    "to": "diego.ruiz@saharaucpartners.example",
    "date": "2024-06-06",
    "subject": "License alignment check",
    "sentiment": "neutral",
    "status": "sent",
    "body": "Hello Diego Ruiz,\n\nFollowing our discussion on Sahara UC Partners's deployment, attached is the Standard outline with SC counts.\n\nChris"
  },
  {
    "id": "eml-0040",
    "partnerId": "prt-045",
    "partnerName": "Dublin Voice",
    "from": "henrik.larsson@dublinvoice.example",
    "to": "sam.rivera@3cx-sales.example",
    "date": "2024-07-08",
    "subject": "License alignment check",
    "sentiment": "positive",
    "status": "sent",
    "body": "Henrik Larsson wrote:\nWe need pricing for 76 SC and clarity on private cloud vs hosted.\n\nThanks"
  },
  {
    "id": "eml-0041",
    "partnerId": "prt-048",
    "partnerName": "Edinburgh UC",
    "from": "ana.popescu@edinburghuc.example",
    "to": "jordan.lee@3cx-sales.example",
    "date": "2024-07-17",
    "subject": "Meeting recap & action items",
    "sentiment": "positive",
    "status": "sent",
    "body": "Ana Popescu wrote:\nWe need pricing for 205 SC and clarity on private cloud vs hosted.\n\nThanks"
  },
  {
    "id": "eml-0042",
    "partnerId": "prt-031",
    "partnerName": "Mexico City VoIP",
    "from": "tomasz.kowalski@3cx-sales.example",
    "to": "marco.silva@mexicocityvoip.example",
    "date": "2024-04-28",
    "subject": "Meeting recap & action items",
    "sentiment": "neutral",
    "status": "sent",
    "body": "Hello Marco Silva,\n\nFollowing our discussion on Mexico City VoIP's deployment, attached is the Pro outline with SC counts.\n\nTomasz"
  },
  {
    "id": "eml-0043",
    "partnerId": "prt-032",
    "partnerName": "São Paulo Ring",
    "from": "chris.okonkwo@3cx-sales.example",
    "to": "ingrid.berg@sopauloring.example",
    "date": "2024-09-28",
    "subject": "Meeting recap & action items",
    "sentiment": "negative",
    "status": "sent",
    "body": "Hello Ingrid Berg,\n\nFollowing our discussion on São Paulo Ring's deployment, attached is the Pro outline with SC counts.\n\nChris"
  },
  {
    "id": "eml-0044",
    "partnerId": "prt-012",
    "partnerName": "Metro Connect France",
    "from": "ingrid.berg@metroconnectfrance.example",
    "to": "chris.okonkwo@3cx-sales.example",
    "date": "2025-02-27",
    "subject": "Hosting renewal — next steps",
    "sentiment": "neutral",
    "status": "sent",
    "body": "Ingrid Berg wrote:\nWe need pricing for 79 SC and clarity on private cloud vs hosted.\n\nThanks"
  },
  {
    "id": "eml-0045",
    "partnerId": "prt-041",
    "partnerName": "Lisbon Ring",
    "from": "marco.silva@lisbonring.example",
    "to": "jordan.lee@3cx-sales.example",
    "date": "2026-05-01",
    "subject": "SC expansion quote",
    "sentiment": "positive",
    "status": "scheduled_draft",
    "body": "Marco Silva wrote:\nWe need pricing for 33 SC and clarity on private cloud vs hosted.\n\nThanks"
  },
  {
    "id": "eml-0046",
    "partnerId": "prt-006",
    "partnerName": "Baltic Telecom Solutions",
    "from": "yuki.tanaka@baltictelecomsolutions.example",
    "to": "jordan.lee@3cx-sales.example",
    "date": "2024-02-06",
    "subject": "License alignment check",
    "sentiment": "neutral",
    "status": "sent",
    "body": "Yuki Tanaka wrote:\nWe need pricing for 115 SC and clarity on private cloud vs hosted.\n\nThanks"
  },
  {
    "id": "eml-0047",
    "partnerId": "prt-002",
    "partnerName": "TeleConnect Iberia",
    "from": "morgan.blake@3cx-sales.example",
    "to": "ingrid.berg@teleconnectiberia.example",
    "date": "2024-03-07",
    "subject": "Follow-up: partner QBR",
    "sentiment": "neutral",
    "status": "sent",
    "body": "Hello Ingrid Berg,\n\nFollowing our discussion on TeleConnect Iberia's deployment, attached is the Pro outline with SC counts.\n\nMorgan"
  },
  {
    "id": "eml-0048",
    "partnerId": "prt-035",
    "partnerName": "Warsaw Voice Partners",
    "from": "james.whitaker@3cx-sales.example",
    "to": "henrik.larsson@warsawvoicepartners.example",
    "date": "2025-01-16",
    "subject": "License alignment check",
    "sentiment": "negative",
    "status": "sent",
    "body": "Hello Henrik Larsson,\n\nFollowing our discussion on Warsaw Voice Partners's deployment, attached is the Enterprise outline with SC counts.\n\nJames"
  },
  {
    "id": "eml-0049",
    "partnerId": "prt-029",
    "partnerName": "Vancouver Voice",
    "from": "viktor.novak@vancouvervoice.example",
    "to": "alex.chen@3cx-sales.example",
    "date": "2026-04-28",
    "subject": "Follow-up: partner QBR",
    "sentiment": "neutral",
    "status": "scheduled_draft",
    "body": "Viktor Novak wrote:\nWe need pricing for 136 SC and clarity on private cloud vs hosted.\n\nThanks"
  },
  {
    "id": "eml-0050",
    "partnerId": "prt-006",
    "partnerName": "Baltic Telecom Solutions",
    "from": "tomasz.kowalski@3cx-sales.example",
    "to": "yuki.tanaka@baltictelecomsolutions.example",
    "date": "2024-06-21",
    "subject": "Meeting recap & action items",
    "sentiment": "positive",
    "status": "sent",
    "body": "Hello Yuki Tanaka,\n\nFollowing our discussion on Baltic Telecom Solutions's deployment, attached is the Standard outline with SC counts.\n\nTomasz"
  },
  {
    "id": "eml-0051",
    "partnerId": "prt-014",
    "partnerName": "Danube Digital",
    "from": "priya.desai@3cx-sales.example",
    "to": "fatima.hassan@danubedigital.example",
    "date": "2024-09-07",
    "subject": "Follow-up: partner QBR",
    "sentiment": "positive",
    "status": "sent",
    "body": "Hello Fatima Hassan,\n\nFollowing our discussion on Danube Digital's deployment, attached is the Standard outline with SC counts.\n\nPriya"
  },
  {
    "id": "eml-0052",
    "partnerId": "prt-020",
    "partnerName": "Nairobi Voice Hub",
    "from": "chris.okonkwo@3cx-sales.example",
    "to": "zara.khan@nairobivoicehub.example",
    "date": "2024-08-06",
    "subject": "Follow-up: partner QBR",
    "sentiment": "neutral",
    "status": "sent",
    "body": "Hello Zara Khan,\n\nFollowing our discussion on Nairobi Voice Hub's deployment, attached is the Pro outline with SC counts.\n\nChris"
  },
  {
    "id": "eml-0053",
    "partnerId": "prt-038",
    "partnerName": "Bucharest UC",
    "from": "ana.popescu@bucharestuc.example",
    "to": "priya.desai@3cx-sales.example",
    "date": "2024-12-21",
    "subject": "Meeting recap & action items",
    "sentiment": "positive",
    "status": "sent",
    "body": "Ana Popescu wrote:\nWe need pricing for 29 SC and clarity on private cloud vs hosted.\n\nThanks"
  },
  {
    "id": "eml-0054",
    "partnerId": "prt-014",
    "partnerName": "Danube Digital",
    "from": "fatima.hassan@danubedigital.example",
    "to": "chris.okonkwo@3cx-sales.example",
    "date": "2024-05-05",
    "subject": "License alignment check",
    "sentiment": "negative",
    "status": "sent",
    "body": "Fatima Hassan wrote:\nWe need pricing for 226 SC and clarity on private cloud vs hosted.\n\nThanks"
  },
  {
    "id": "eml-0055",
    "partnerId": "prt-015",
    "partnerName": "Caspian Telecom",
    "from": "henrik.larsson@caspiantelecom.example",
    "to": "james.whitaker@3cx-sales.example",
    "date": "2024-10-02",
    "subject": "Hosting renewal — next steps",
    "sentiment": "neutral",
    "status": "sent",
    "body": "Henrik Larsson wrote:\nWe need pricing for 132 SC and clarity on private cloud vs hosted.\n\nThanks"
  },
  {
    "id": "eml-0056",
    "partnerId": "prt-008",
    "partnerName": "Alpine Voice Systems",
    "from": "sam.rivera@3cx-sales.example",
    "to": "ana.popescu@alpinevoicesystems.example",
    "date": "2024-06-28",
    "subject": "Follow-up: partner QBR",
    "sentiment": "negative",
    "status": "sent",
    "body": "Hello Ana Popescu,\n\nFollowing our discussion on Alpine Voice Systems's deployment, attached is the Pro outline with SC counts.\n\nSam"
  },
  {
    "id": "eml-0057",
    "partnerId": "prt-038",
    "partnerName": "Bucharest UC",
    "from": "ana.popescu@bucharestuc.example",
    "to": "priya.desai@3cx-sales.example",
    "date": "2024-03-02",
    "subject": "Hosting renewal — next steps",
    "sentiment": "neutral",
    "status": "sent",
    "body": "Ana Popescu wrote:\nWe need pricing for 28 SC and clarity on private cloud vs hosted.\n\nThanks"
  },
  {
    "id": "eml-0058",
    "partnerId": "prt-022",
    "partnerName": "Tokyo UC Partners",
    "from": "ingrid.berg@tokyoucpartners.example",
    "to": "elena.vogel@3cx-sales.example",
    "date": "2025-02-28",
    "subject": "Meeting recap & action items",
    "sentiment": "positive",
    "status": "sent",
    "body": "Ingrid Berg wrote:\nWe need pricing for 236 SC and clarity on private cloud vs hosted.\n\nThanks"
  },
  {
    "id": "eml-0059",
    "partnerId": "prt-008",
    "partnerName": "Alpine Voice Systems",
    "from": "jordan.lee@3cx-sales.example",
    "to": "ana.popescu@alpinevoicesystems.example",
    "date": "2024-01-11",
    "subject": "Meeting recap & action items",
    "sentiment": "neutral",
    "status": "sent",
    "body": "Hello Ana Popescu,\n\nFollowing our discussion on Alpine Voice Systems's deployment, attached is the Enterprise outline with SC counts.\n\nJordan"
  },
  {
    "id": "eml-0060",
    "partnerId": "prt-050",
    "partnerName": "Stockholm Ring",
    "from": "jordan.lee@3cx-sales.example",
    "to": "zara.khan@stockholmring.example",
    "date": "2024-01-16",
    "subject": "Meeting recap & action items",
    "sentiment": "neutral",
    "status": "sent",
    "body": "Hello Zara Khan,\n\nFollowing our discussion on Stockholm Ring's deployment, attached is the Enterprise outline with SC counts.\n\nJordan"
  },
  {
    "id": "eml-0061",
    "partnerId": "prt-031",
    "partnerName": "Mexico City VoIP",
    "from": "alex.chen@3cx-sales.example",
    "to": "marco.silva@mexicocityvoip.example",
    "date": "2026-04-26",
    "subject": "SC expansion quote",
    "sentiment": "neutral",
    "status": "scheduled_draft",
    "body": "Hello Marco Silva,\n\nFollowing our discussion on Mexico City VoIP's deployment, attached is the Standard outline with SC counts.\n\nAlex"
  },
  {
    "id": "eml-0062",
    "partnerId": "prt-008",
    "partnerName": "Alpine Voice Systems",
    "from": "ana.popescu@alpinevoicesystems.example",
    "to": "priya.desai@3cx-sales.example",
    "date": "2024-05-02",
    "subject": "PBX renewal options",
    "sentiment": "neutral",
    "status": "sent",
    "body": "Ana Popescu wrote:\nWe need pricing for 64 SC and clarity on private cloud vs hosted.\n\nThanks"
  },
  {
    "id": "eml-0063",
    "partnerId": "prt-004",
    "partnerName": "Unified Comms UK",
    "from": "fatima.hassan@unifiedcommsuk.example",
    "to": "morgan.blake@3cx-sales.example",
    "date": "2024-04-20",
    "subject": "Follow-up: partner QBR",
    "sentiment": "positive",
    "status": "sent",
    "body": "Fatima Hassan wrote:\nWe need pricing for 29 SC and clarity on private cloud vs hosted.\n\nThanks"
  },
  {
    "id": "eml-0064",
    "partnerId": "prt-025",
    "partnerName": "Sydney PBX Group",
    "from": "sofia.martins@3cx-sales.example",
    "to": "henrik.larsson@sydneypbxgroup.example",
    "date": "2025-01-05",
    "subject": "License alignment check",
    "sentiment": "positive",
    "status": "sent",
    "body": "Hello Henrik Larsson,\n\nFollowing our discussion on Sydney PBX Group's deployment, attached is the Standard outline with SC counts.\n\nSofia"
  },
  {
    "id": "eml-0065",
    "partnerId": "prt-019",
    "partnerName": "Lagos Connect",
    "from": "james.whitaker@3cx-sales.example",
    "to": "viktor.novak@lagosconnect.example",
    "date": "2024-09-26",
    "subject": "PBX renewal options",
    "sentiment": "neutral",
    "status": "sent",
    "body": "Hello Viktor Novak,\n\nFollowing our discussion on Lagos Connect's deployment, attached is the Pro outline with SC counts.\n\nJames"
  },
  {
    "id": "eml-0066",
    "partnerId": "prt-031",
    "partnerName": "Mexico City VoIP",
    "from": "sofia.martins@3cx-sales.example",
    "to": "marco.silva@mexicocityvoip.example",
    "date": "2024-07-19",
    "subject": "Follow-up: partner QBR",
    "sentiment": "neutral",
    "status": "sent",
    "body": "Hello Marco Silva,\n\nFollowing our discussion on Mexico City VoIP's deployment, attached is the Pro outline with SC counts.\n\nSofia"
  },
  {
    "id": "eml-0067",
    "partnerId": "prt-016",
    "partnerName": "Red Sea Voice",
    "from": "sam.rivera@3cx-sales.example",
    "to": "yuki.tanaka@redseavoice.example",
    "date": "2024-04-21",
    "subject": "SC expansion quote",
    "sentiment": "neutral",
    "status": "sent",
    "body": "Hello Yuki Tanaka,\n\nFollowing our discussion on Red Sea Voice's deployment, attached is the Pro outline with SC counts.\n\nSam"
  },
  {
    "id": "eml-0068",
    "partnerId": "prt-035",
    "partnerName": "Warsaw Voice Partners",
    "from": "henrik.larsson@warsawvoicepartners.example",
    "to": "elena.vogel@3cx-sales.example",
    "date": "2024-11-19",
    "subject": "Meeting recap & action items",
    "sentiment": "positive",
    "status": "sent",
    "body": "Henrik Larsson wrote:\nWe need pricing for 143 SC and clarity on private cloud vs hosted.\n\nThanks"
  },
  {
    "id": "eml-0069",
    "partnerId": "prt-013",
    "partnerName": "Rhine Valley IT",
    "from": "sam.rivera@3cx-sales.example",
    "to": "luis.garcía@rhinevalleyit.example",
    "date": "2024-12-06",
    "subject": "SC expansion quote",
    "sentiment": "neutral",
    "status": "sent",
    "body": "Hello Luis García,\n\nFollowing our discussion on Rhine Valley IT's deployment, attached is the Enterprise outline with SC counts.\n\nSam"
  },
  {
    "id": "eml-0070",
    "partnerId": "prt-010",
    "partnerName": "Great Lakes UC",
    "from": "zara.khan@greatlakesuc.example",
    "to": "chris.okonkwo@3cx-sales.example",
    "date": "2024-06-28",
    "subject": "License alignment check",
    "sentiment": "neutral",
    "status": "sent",
    "body": "Zara Khan wrote:\nWe need pricing for 184 SC and clarity on private cloud vs hosted.\n\nThanks"
  },
  {
    "id": "eml-0071",
    "partnerId": "prt-032",
    "partnerName": "São Paulo Ring",
    "from": "jordan.lee@3cx-sales.example",
    "to": "ingrid.berg@sopauloring.example",
    "date": "2024-04-25",
    "subject": "PBX renewal options",
    "sentiment": "neutral",
    "status": "sent",
    "body": "Hello Ingrid Berg,\n\nFollowing our discussion on São Paulo Ring's deployment, attached is the Pro outline with SC counts.\n\nJordan"
  },
  {
    "id": "eml-0072",
    "partnerId": "prt-014",
    "partnerName": "Danube Digital",
    "from": "sam.rivera@3cx-sales.example",
    "to": "fatima.hassan@danubedigital.example",
    "date": "2024-07-03",
    "subject": "License alignment check",
    "sentiment": "neutral",
    "status": "sent",
    "body": "Hello Fatima Hassan,\n\nFollowing our discussion on Danube Digital's deployment, attached is the Standard outline with SC counts.\n\nSam"
  }
]